gemseo_calibration/__init__.py
gemseo_calibration/calibrator.py
gemseo_calibration/measure.py
gemseo_calibration/post_processor.py
gemseo_calibration/scenario.py
gemseo_calibration/measures/__init__.py
gemseo_calibration/measures/factory.py
gemseo_calibration/measures/iae.py
gemseo_calibration/measures/integrated_measure.py
gemseo_calibration/measures/ise.py
gemseo_calibration/measures/mae.py
gemseo_calibration/measures/mean_measure.py
gemseo_calibration/measures/mse.py
gemseo_calibration/post/__init__.py
gemseo_calibration/post/_matplotlib_multiple_scatter.py
gemseo_calibration/post/factory.py
gemseo_calibration/post/multiple_scatter.py
gemseo_calibration/post/data_versus_model/__init__.py
gemseo_calibration/post/data_versus_model/post.py
gemseo_calibration/post/data_versus_model/settings.py
gemseo_calibration/problems/mock_with_curves/__init__.py
gemseo_calibration/problems/mock_with_curves/mock_with_curves.py
gemseo_calibration_vimseo-3.0.2.dist-info/licenses/LICENSE.txt
gemseo_calibration_vimseo-3.0.2.dist-info/METADATA
gemseo_calibration_vimseo-3.0.2.dist-info/WHEEL
gemseo_calibration_vimseo-3.0.2.dist-info/entry_points.txt
gemseo_calibration_vimseo-3.0.2.dist-info/top_level.txt
gemseo_calibration_vimseo-3.0.2.dist-info/RECORD
